mujoco_sysid/__init__.py
mujoco_sysid/convert.py
mujoco_sysid/parameters.py
mujoco_sysid/regressors.py
mujoco_sysid/utils.py
mujoco_sysid/mjx/__init__.py
mujoco_sysid/mjx/convert.py
mujoco_sysid/mjx/parameters.py
mujoco_sysid/mjx/regressors.py
mujoco_sysid-0.2.1.dist-info/METADATA
mujoco_sysid-0.2.1.dist-info/WHEEL
mujoco_sysid-0.2.1.dist-info/top_level.txt
mujoco_sysid-0.2.1.dist-info/RECORD
