Metadata-Version: 2.1
Name: mujoco_sysid
Version: 0.2.1
Summary: MuJoCo System Identification tools
Author-email: Lev Kozlov <kozlov.l.a10@gmail.com>, Simeon Nedelchev <simkaned@gmail.com>
Project-URL: homepage, https://github.com/lvjonok/mujoco-sysid
Project-URL: repository, https://github.com/lvjonok/mujoco-sysid.git
Requires-Python: >=3.8
Requires-Dist: mujoco
Requires-Dist: numpy-quaternion
Provides-Extra: examples
Requires-Dist: ipykernel; extra == "examples"
Requires-Dist: dm-control; extra == "examples"
Requires-Dist: scipy; extra == "examples"
Requires-Dist: matplotlib; extra == "examples"
Requires-Dist: robot-descriptions; extra == "examples"
Requires-Dist: mediapy; extra == "examples"
Provides-Extra: mjx
Requires-Dist: mujoco-mjx; extra == "mjx"
Requires-Dist: jax[cuda12]; extra == "mjx"
Provides-Extra: mjx_cpu
Requires-Dist: mujoco-mjx; extra == "mjx-cpu"
Requires-Dist: jax; extra == "mjx-cpu"
